[{"vardas":"Povilas288","pavarde":"Bar288","amzius":78,"miestas":"Kaunas"},{"vardas":"Povilas617","pavarde":"Bar617","amzius":47,"miestas":"Kaunas"},{"vardas":"Povilas977","pavarde":"Bar977","amzius":73,"miestas":"Kaunas"},{"vardas":"Povilas472","pavarde":"Bar472","amzius":45,"miestas":"Kaunas"},{"vardas":"Povilas607","pavarde":"Bar607","amzius":30,"miestas":"Kaunas"},{"vardas":"Povilas733","pavarde":"Bar733","amzius":35,"miestas":"Kaunas"},{"vardas":"Povilas997","pavarde":"Bar997","amzius":78,"miestas":"Kaunas"},{"vardas":"Povilas855","pavarde":"Bar855","amzius":79,"miestas":"Kaunas"},{"vardas":"Povilas543","pavarde":"Bar543","amzius":57,"miestas":"Kaunas"},{"vardas":"Povilas401","pavarde":"Bar401","amzius":62,"miestas":"Kaunas"},{"vardas":"Povilas906","pavarde":"Bar906","amzius":51,"miestas":"Kaunas"},{"vardas":"Povilas500","pavarde":"Bar500","amzius":53,"miestas":"Kaunas"},{"vardas":"Povilas727","pavarde":"Bar727","amzius":41,"miestas":"Kaunas"},{"vardas":"Povilas641","pavarde":"Bar641","amzius":86,"miestas":"Kaunas"},{"vardas":"Povilas514","pavarde":"Bar514","amzius":50,"miestas":"Kaunas"},{"vardas":"Povilas776","pavarde":"Bar776","amzius":48,"miestas":"Kaunas"},{"vardas":"Povilas484","pavarde":"Bar484","amzius":39,"miestas":"Kaunas"},{"vardas":"Povilas153","pavarde":"Bar153","amzius":96,"miestas":"Kaunas"},{"vardas":"Povilas214","pavarde":"Bar214","amzius":16,"miestas":"Kaunas"},{"vardas":"Povilas238","pavarde":"Bar238","amzius":19,"miestas":"Kaunas"},{"vardas":"Povilas335","pavarde":"Bar335","amzius":56,"miestas":"Kaunas"},{"vardas":"Povilas589","pavarde":"Bar589","amzius":81,"miestas":"Kaunas"},{"vardas":"Povilas536","pavarde":"Bar536","amzius":32,"miestas":"Kaunas"},{"vardas":"Povilas756","pavarde":"Bar756","amzius":45,"miestas":"Kaunas"},{"vardas":"Povilas323","pavarde":"Bar323","amzius":99,"miestas":"Kaunas"},{"vardas":"Povilas626","pavarde":"Bar626","amzius":25,"miestas":"Kaunas"},{"vardas":"Povilas852","pavarde":"Bar852","amzius":34,"miestas":"Kaunas"},{"vardas":"Povilas768","pavarde":"Bar768","amzius":32,"miestas":"Kaunas"},{"vardas":"Povilas790","pavarde":"Bar790","amzius":16,"miestas":"Kaunas"},{"vardas":"Povilas768","pavarde":"Bar768","amzius":80,"miestas":"Kaunas"},{"vardas":"Povilas536","pavarde":"Bar536","amzius":65,"miestas":"Kaunas"},{"vardas":"Povilas551","pavarde":"Bar551","amzius":33,"miestas":"Kaunas"},{"vardas":"Povilas446","pavarde":"Bar446","amzius":93,"miestas":"Kaunas"},{"vardas":"Povilas838","pavarde":"Bar838","amzius":12,"miestas":"Kaunas"},{"vardas":"Povilas612","pavarde":"Bar612","amzius":74,"miestas":"Kaunas"},{"vardas":"Povilas397","pavarde":"Bar397","amzius":78,"miestas":"Kaunas"},{"vardas":"Povilas548","pavarde":"Bar548","amzius":19,"miestas":"Kaunas"},{"vardas":"Povilas314","pavarde":"Bar314","amzius":32,"miestas":"Kaunas"},{"vardas":"Povilas936","pavarde":"Bar936","amzius":65,"miestas":"Kaunas"},{"vardas":"Povilas772","pavarde":"Bar772","amzius":75,"miestas":"Kaunas"},{"vardas":"Povilas491","pavarde":"Bar491","amzius":60,"miestas":"Kaunas"},{"vardas":"Povilas808","pavarde":"Bar808","amzius":99,"miestas":"Kaunas"},{"vardas":"Povilas314","pavarde":"Bar314","amzius":24,"miestas":"Kaunas"},{"vardas":"Povilas122","pavarde":"Bar122","amzius":41,"miestas":"Kaunas"},{"vardas":"Povilas567","pavarde":"Bar567","amzius":16,"miestas":"Kaunas"},{"vardas":"Povilas853","pavarde":"Bar853","amzius":81,"miestas":"Kaunas"},{"vardas":"Povilas178","pavarde":"Bar178","amzius":89,"miestas":"Kaunas"},{"vardas":"Povilas876","pavarde":"Bar876","amzius":95,"miestas":"Kaunas"},{"vardas":"Povilas891","pavarde":"Bar891","amzius":25,"miestas":"Kaunas"},{"vardas":"Povilas337","pavarde":"Bar337","amzius":27,"miestas":"Kaunas"},{"vardas":"Povilas168","pavarde":"Bar168","amzius":16,"miestas":"Kaunas"},{"vardas":"Povilas375","pavarde":"Bar375","amzius":33,"miestas":"Kaunas"},{"vardas":"Povilas728","pavarde":"Bar728","amzius":32,"miestas":"Kaunas"},{"vardas":"Povilas825","pavarde":"Bar825","amzius":65,"miestas":"Kaunas"},{"vardas":"Povilas850","pavarde":"Bar850","amzius":90,"miestas":"Kaunas"},{"vardas":"Povilas642","pavarde":"Bar642","amzius":35,"miestas":"Kaunas"},{"vardas":"Povilas590","pavarde":"Bar590","amzius":69,"miestas":"Kaunas"},{"vardas":"Povilas537","pavarde":"Bar537","amzius":38,"miestas":"Kaunas"},{"vardas":"Povilas492","pavarde":"Bar492","amzius":70,"miestas":"Kaunas"},{"vardas":"Povilas362","pavarde":"Bar362","amzius":37,"miestas":"Kaunas"},{"vardas":"Povilas641","pavarde":"Bar641","amzius":70,"miestas":"Kaunas"},{"vardas":"Povilas742","pavarde":"Bar742","amzius":74,"miestas":"Kaunas"},{"vardas":"Povilas415","pavarde":"Bar415","amzius":43,"miestas":"Kaunas"},{"vardas":"Povilas476","pavarde":"Bar476","amzius":35,"miestas":"Kaunas"},{"vardas":"Povilas156","pavarde":"Bar156","amzius":97,"miestas":"Kaunas"},{"vardas":"Povilas542","pavarde":"Bar542","amzius":27,"miestas":"Kaunas"},{"vardas":"Povilas847","pavarde":"Bar847","amzius":77,"miestas":"Kaunas"},{"vardas":"Povilas395","pavarde":"Bar395","amzius":72,"miestas":"Kaunas"},{"vardas":"Povilas236","pavarde":"Bar236","amzius":43,"miestas":"Kaunas"},{"vardas":"Povilas607","pavarde":"Bar607","amzius":10,"miestas":"Kaunas"},{"vardas":"Povilas183","pavarde":"Bar183","amzius":42,"miestas":"Kaunas"},{"vardas":"Povilas467","pavarde":"Bar467","amzius":98,"miestas":"Kaunas"},{"vardas":"Povilas198","pavarde":"Bar198","amzius":73,"miestas":"Kaunas"},{"vardas":"Povilas755","pavarde":"Bar755","amzius":21,"miestas":"Kaunas"},{"vardas":"Povilas855","pavarde":"Bar855","amzius":87,"miestas":"Kaunas"},{"vardas":"Povilas275","pavarde":"Bar275","amzius":36,"miestas":"Kaunas"},{"vardas":"Povilas488","pavarde":"Bar488","amzius":51,"miestas":"Kaunas"},{"vardas":"Povilas205","pavarde":"Bar205","amzius":27,"miestas":"Kaunas"},{"vardas":"Povilas822","pavarde":"Bar822","amzius":14,"miestas":"Kaunas"},{"vardas":"Povilas111","pavarde":"Bar111","amzius":39,"miestas":"Kaunas"},{"vardas":"Povilas780","pavarde":"Bar780","amzius":94,"miestas":"Kaunas"},{"vardas":"Povilas618","pavarde":"Bar618","amzius":35,"miestas":"Kaunas"},{"vardas":"Povilas785","pavarde":"Bar785","amzius":95,"miestas":"Kaunas"},{"vardas":"Povilas575","pavarde":"Bar575","amzius":33,"miestas":"Kaunas"},{"vardas":"Povilas523","pavarde":"Bar523","amzius":91,"miestas":"Kaunas"},{"vardas":"Povilas372","pavarde":"Bar372","amzius":93,"miestas":"Kaunas"},{"vardas":"Povilas392","pavarde":"Bar392","amzius":47,"miestas":"Kaunas"},{"vardas":"Povilas949","pavarde":"Bar949","amzius":35,"miestas":"Kaunas"},{"vardas":"Povilas973","pavarde":"Bar973","amzius":12,"miestas":"Kaunas"},{"vardas":"Povilas541","pavarde":"Bar541","amzius":20,"miestas":"Kaunas"},{"vardas":"Povilas265","pavarde":"Bar265","amzius":18,"miestas":"Kaunas"},{"vardas":"Povilas874","pavarde":"Bar874","amzius":58,"miestas":"Kaunas"},{"vardas":"Povilas562","pavarde":"Bar562","amzius":77,"miestas":"Kaunas"},{"vardas":"Povilas905","pavarde":"Bar905","amzius":53,"miestas":"Kaunas"},{"vardas":"Povilas882","pavarde":"Bar882","amzius":74,"miestas":"Kaunas"},{"vardas":"Povilas910","pavarde":"Bar910","amzius":11,"miestas":"Kaunas"},{"vardas":"Povilas593","pavarde":"Bar593","amzius":23,"miestas":"Kaunas"},{"vardas":"Povilas769","pavarde":"Bar769","amzius":36,"miestas":"Kaunas"},{"vardas":"Povilas775","pavarde":"Bar775","amzius":19,"miestas":"Kaunas"},{"vardas":"Povilas503","pavarde":"Bar503","amzius":66,"miestas":"Kaunas"},{"vardas":"Povilas462","pavarde":"Bar462","amzius":99,"miestas":"Kaunas"},{"vardas":"Povilas176","pavarde":"Bar176","amzius":22,"miestas":"Kaunas"},{"vardas":"Povilas632","pavarde":"Bar632","amzius":36,"miestas":"Kaunas"},{"vardas":"Povilas674","pavarde":"Bar674","amzius":71,"miestas":"Kaunas"},{"vardas":"Povilas131","pavarde":"Bar131","amzius":62,"miestas":"Kaunas"},{"vardas":"Povilas656","pavarde":"Bar656","amzius":92,"miestas":"Kaunas"},{"vardas":"Povilas951","pavarde":"Bar951","amzius":59,"miestas":"Kaunas"},{"vardas":"Povilas357","pavarde":"Bar357","amzius":56,"miestas":"Kaunas"},{"vardas":"Povilas904","pavarde":"Bar904","amzius":37,"miestas":"Kaunas"},{"vardas":"Povilas484","pavarde":"Bar484","amzius":28,"miestas":"Kaunas"},{"vardas":"Povilas981","pavarde":"Bar981","amzius":57,"miestas":"Kaunas"},{"vardas":"Povilas736","pavarde":"Bar736","amzius":32,"miestas":"Kaunas"}]